<?xml version="1.0" encoding="UTF-8" ?>
<extension type="package" version="2.5" method="upgrade">
	<name>JEvents - Attendance, Invitations and Reminders</name>
	<packagename>rsvppro</packagename>
	<version>3.0.12</version>
	<url>http://www.jevents.net</url>
	<creationDate>December 2013</creationDate>
	<author>Geraint Edwards</author>
	<copyright>(C) 2012-2013 GWE Systems Ltd</copyright>
	<authorEmail></authorEmail>
	<authorUrl>www.gwesystems.com</authorUrl>
	<packager>GWE Systems Ltd</packager>
	<packagerurl>http://www.jevents.net</packagerurl>
	<description>JEvents Attendance, Invitations and Reminders Package</description>
	<update></update>
	<scriptfile>installpkg.php</scriptfile>
	<files>
		<file type="component" id="com_jevrsvppro" >jevrsvppro.zip</file>
		<file type="plugin" id="jevrsvppro" group="jevents">plugin.zip</file>
		<file type="plugin" id="authorizenet" group="rsvppro">authorizenet.zip</file>
		<file type="plugin" id="manual" group="rsvppro">manual.zip</file>
		<file type="plugin" id="paypalipn" group="rsvppro">paypalipn.zip</file>
		<file type="plugin" id="virtuemart" group="rsvppro">virtuemart.zip</file>
		<file type="plugin" id="rsvppro" group="vmcoupon">vmcoupon.zip</file>
		<file type="plugin" id="rsvppro" group="vmcustom">vmcustom.zip</file>
	</files>
</extension>